exposapi/__init__.py
exposapi/apps.py
exposapi/auth_handler.py
exposapi/config.py
exposapi/responses_command.py
exposapi/urls.py
exposapi/views.py
wagtail_exposapi-1.0.0.dist-info/LICENSE
wagtail_exposapi-1.0.0.dist-info/METADATA
wagtail_exposapi-1.0.0.dist-info/WHEEL
wagtail_exposapi-1.0.0.dist-info/top_level.txt
wagtail_exposapi-1.0.0.dist-info/RECORD
