Metadata-Version: 2.1
Name: wagtail-exposapi
Version: 1.0.0
Summary: Expose Wagtail internals via a REST API for use while developing and testing Wagtail sites.
Author-email: Nick Moreton <nickmoreton@me.com>
License: MIT License
Classifier: License :: OSI Approved :: MIT License
Classifier: Operating System :: OS Independent
Classifier: Programming Language :: Python
Classifier: Programming Language :: Python :: 3
Classifier: Programming Language :: Python :: 3.8
Classifier: Programming Language :: Python :: 3.9
Classifier: Programming Language :: Python :: 3.10
Classifier: Programming Language :: Python :: 3.11
Classifier: Programming Language :: Python :: 3.12
Classifier: Framework :: Django
Classifier: Framework :: Django :: 3.2
Classifier: Framework :: Django :: 4.1
Classifier: Framework :: Django :: 4.2
Classifier: Framework :: Django :: 5.0
Classifier: Framework :: Wagtail
Classifier: Framework :: Wagtail :: 4
Classifier: Framework :: Wagtail :: 5
Classifier: Framework :: Wagtail :: 6
Requires-Python: >=3.8
License-File: LICENSE
Requires-Dist: Wagtail <6.1,>=4.1
Requires-Dist: Django <5.1,>=3.2
Provides-Extra: development
Requires-Dist: black ==24.2.0 ; extra == 'development'
Requires-Dist: flake8 ==7.0.0 ; extra == 'development'
Requires-Dist: isort ==5.13.2 ; extra == 'development'
Provides-Extra: modeladmin2
Requires-Dist: wagtail-modeladmin <3.0,>=2.0 ; extra == 'modeladmin2'
Provides-Extra: testing
Requires-Dist: coverage ==7.4.1 ; extra == 'testing'
Requires-Dist: responses ==0.24.1 ; extra == 'testing'
